pits/__init__.py
pits-0.1.2.dist-info/LICENSE
pits-0.1.2.dist-info/METADATA
pits-0.1.2.dist-info/WHEEL
pits-0.1.2.dist-info/top_level.txt
pits-0.1.2.dist-info/RECORD
