Metadata-Version: 2.1
Name: pits
Version: 0.1.2
Summary: Point-in-time Storage.
Author-email: Sun Yijiang <sunyijiang@gmail.com>
Project-URL: Homepage, https://github.com/sunyj/pits
Project-URL: Bug Tracker, https://github.com/sunyj/pits/issues
Classifier: Programming Language :: Python :: 3
Classifier: License :: OSI Approved :: MIT License
Classifier: Operating System :: OS Independent
Requires-Python: >=3.4
License-File: LICENSE
